server/__init__.py
server/server.py
server/common/__init__.py
server/common/decorators.py
server/common/descriptors.py
server/common/errors.py
server/common/metaclass.py
server/common/utils.py
server/common/variables.py
server/logs/__init__.py
server/logs/app_log_config.py
server/logs/client_log_config.py
server/logs/server_log_config.py
server/server/__init__.py
server/server/add_user.py
server/server/config_window.py
server/server/core.py
server/server/db.py
server/server/main_window.py
server/server/remove_user.py
server/server/stat_window.py
server_messanger-1.2.data/scripts/server_run
server_messanger-1.2.dist-info/METADATA
server_messanger-1.2.dist-info/WHEEL
server_messanger-1.2.dist-info/top_level.txt
server_messanger-1.2.dist-info/RECORD
